{"job_id": 20000, "params": {"CPU": [8.0], "Provider": ["aws"], "Category": ["General"]}, "vars": {"selector": "exact_match", "deployer": "vbench", "log_converter": "vbench", "docker_image": "severalnines/sysbench", "vbench_type": "vod", "vbench_filter": "house"}, "timestamp": "20190717194219", "base_dir": "/mnt/d/OneDrive - University of St Andrews/Everything/Uni/Data Intensive Analysis/Dissertation/AutomatedBayesCloudSelection", "selection": {"instance": "m5.2xlarge", "price": 0.384}, "logs": "#video, psnr_ratio, bitrate_ratio, speed_ratio, vod score\nhouse_1920x1080_30.mkv,1.00007668143,0.999466524407,0.685215213962,0.684849668369\n", "value": -1.7834626780442706}